credible/__init__.py
credible/curves.py
credible/plot.py
credible/utils.py
credible/bayesian/functors.py
credible/bayesian/kfold.py
credible/bayesian/metrics.py
credible/bayesian/utils.py
credible/frequentist/functors.py
credible/frequentist/utils.py
credible-1.0.3.dist-info/METADATA
credible-1.0.3.dist-info/WHEEL
credible-1.0.3.dist-info/RECORD
