Metadata-Version: 2.4
Name: credible
Version: 1.0.3
Summary: This library contains implementations of some scikit-learn metrics with confidence intervals
Project-URL: documentation, https://credible.readthedocs.io/en/v1.0.3/
Project-URL: homepage, https://pypi.org/project/credible
Project-URL: repository, https://gitlab.idiap.ch/medai/software/credible
Project-URL: changelog, https://gitlab.idiap.ch/medai/software/credible/-/releases
Author-email: Andre Anjos <andre.anjos@idiap.ch>
License-Expression: GPL-3.0-or-later
Classifier: Development Status :: 4 - Beta
Classifier: Intended Audience :: Developers
Classifier: License :: OSI Approved :: GNU General Public License v3 (GPLv3)
Classifier: Natural Language :: English
Classifier: Programming Language :: Python :: 3
Classifier: Topic :: Software Development :: Libraries :: Python Modules
Requires-Python: >=3.10
Requires-Dist: matplotlib
Requires-Dist: numpy
Requires-Dist: scikit-learn
Requires-Dist: scipy
Provides-Extra: doc
Requires-Dist: auto-intersphinx; extra == 'doc'
Requires-Dist: furo; extra == 'doc'
Requires-Dist: sphinx; extra == 'doc'
Requires-Dist: sphinx-autodoc-typehints; extra == 'doc'
Requires-Dist: sphinx-copybutton; extra == 'doc'
Requires-Dist: sphinx-inline-tabs; extra == 'doc'
Provides-Extra: qa
Requires-Dist: pre-commit; extra == 'qa'
Provides-Extra: test
Requires-Dist: pytest; extra == 'test'
Requires-Dist: pytest-cov; extra == 'test'
